<templates>
	<template class="CodeAnalyzer">
		<h1>PWB Code Analyzer</h1>
		<table>
			<tbody>
				<tr>
					<td>
						Directories:<br />
						(Separate with commas)
					</td>
					<td>
						<container id="directories_input" />
					</td>
					<td>
						Search recursively:
					</td>
					<td>
						<container id="recursive_checkbox" />
					</td>
				</tr>
				<tr>
					<td>
						Analyze: <br />
						(CTRL + Left-click to select several)
				 	</td>
					<td>
						<container id="cases_select" />
					</td>
				</tr>
			</tbody>
		</table>
		<div>
			<input type="button" id="analyze_button" value="Analyze" />
		</div>
		<div>
			<container id="output_textarea" />
		</div>
	</template>
</templates>